[{
        "app_name": "IRUATNEC",
        "os_image": [{
                "name": "CentOS 7.1",
                "image_url": "https://cloud.centos.org/centos/7/images/CentOS-7-x86_64-GenericCloud.qcow2",
                "qt": {
                    "version": "4.8",
                    "app_name": "IRUATNEC",
                    "script_url": "https://raw.githubusercontent.com/pipoe2h/calm/webpage/demo/areydemo/qt4.sh"
                }
            },
            {
                "name": "CentOS 8.2",
                "image_url": "https://cloud.centos.org/centos/8/x86_64/images/CentOS-8-GenericCloud-8.2.2004-20200611.2.x86_64.qcow2",
                "qt": {
                    "version": "5.9.4",
                    "app_name": "ELLIACAL",
                    "script_url": "https://raw.githubusercontent.com/pipoe2h/calm/webpage/demo/areydemo/qt5.sh"
                }
            }
        ],
        "compilers": [{
                "name": "Qmake",
                "script_url": "n/a"
            },
            {
                "name": "Make",
                "script_url": "n/a"
            }
        ],
        "editors": [{
            "name": "QtCreator",
            "script_url": ""
        }]
    },
    {
        "app_name": "SSOR",
        "os_image": [{
                "name": "Ubuntu 16.04",
                "image_url": "https://cloud-images.ubuntu.com/releases/xenial/release/ubuntu-16.04-server-cloudimg-amd64-disk1.img",
                "qt": {
                    "version": "n/a",
                    "app_name": "n/a",
                    "script_url": "n/a"
                }
            },
            {
                "name": "Ubuntu 18.04",
                "image_url": "https://cloud-images.ubuntu.com/releases/bionic/release/ubuntu-18.04-server-cloudimg-amd64.img",
                "qt": {
                    "version": "n/a",
                    "app_name": "n/a",
                    "script_url": "n/a"
                }
            }
        ],
        "compilers": [{
                "name": "Cmake",
                "script_url": "https://raw.githubusercontent.com/pipoe2h/calm/webpage/demo/areydemo/cmake.sh"
            },
            {
                "name": "Make",
                "script_url": "n/a"
            }
        ],
        "editors": [{
                "name": "QtCreator",
                "script_url": ""
            },
            {
                "name": "Eclipse",
                "script_url": ""
            },
            {
                "name": "Clion",
                "script_url": ""
            }
        ]
    }
]